flowimds/__init__.py
flowimds/models.py
flowimds/pipeline.py
flowimds/pipeline_old.py
flowimds/py.typed
flowimds/result.py
flowimds/steps/__init__.py
flowimds/steps/base.py
flowimds/steps/binarize.py
flowimds/steps/denoise.py
flowimds/steps/flip.py
flowimds/steps/grayscale.py
flowimds/steps/resize.py
flowimds/steps/rotate.py
flowimds/utils/image_discovery.py
flowimds/utils/image_io.py
flowimds-1.0.2.dist-info/licenses/LICENSE
flowimds-1.0.2.dist-info/METADATA
flowimds-1.0.2.dist-info/WHEEL
flowimds-1.0.2.dist-info/top_level.txt
flowimds-1.0.2.dist-info/RECORD
