Metadata-Version: 2.4
Name: flowimds
Version: 1.0.2
Summary: Batch image directory processing pipelines with reusable steps
Author-email: mori-318 <105962185+mori-318@users.noreply.github.com>
Maintainer-email: mori-318 <105962185+mori-318@users.noreply.github.com>
License: MIT License
Project-URL: Homepage, https://github.com/mori-318/flowimds
Project-URL: Repository, https://github.com/mori-318/flowimds
Project-URL: Documentation, https://github.com/mori-318/flowimds#readme
Keywords: image-processing,pipeline,batch
Classifier: Programming Language :: Python :: 3
Classifier: Programming Language :: Python :: 3.12
Classifier: License :: OSI Approved :: MIT License
Classifier: Operating System :: OS Independent
Classifier: Topic :: Multimedia :: Graphics :: Graphics Conversion
Requires-Python: >=3.12
License-File: LICENSE
Requires-Dist: numpy>=2.2.6
Requires-Dist: opencv-python>=4.12.0.88
Requires-Dist: tqdm>=4.67.1
Dynamic: license-file
